hanser_py_library
