Metadata-Version: 2.1
Name: hanser-py-library
Version: 0.3.4
Summary: Download a book as PDF from https://www.hanser-elibrary.com/
Home-page: https://github.com/vlntnwbr/HanserPyLibrary
Author: Valentin Weber
Author-email: dev@vweber.eu
Maintainer: Valentin Weber
Maintainer-email: dev@vweber.eu
License: GNU GPLv3
Project-URL: Bug Tracker, https://github.com/vlntnwbr/HanserPyLibrary/issues?q=label%3bug
Platform: UNKNOWN
Classifier: Development Status :: 4 - Beta
Classifier: Environment :: Console
Classifier: Intended Audience :: Education
Classifier: Intended Audience :: Science/Research
Classifier: License :: OSI Approved :: GNU Affero General Public License v3
Classifier: Operating System :: OS Independent
Classifier: Programming Language :: Python :: 3 :: Only
Classifier: Topic :: Education
Classifier: Topic :: Scientific/Engineering
Classifier: Topic :: Utilities
Requires-Python: >=3.8
